aghplctools/__init__.py
aghplctools/batch.py
aghplctools/config.py
aghplctools/data_types.py
aghplctools/hplc.py
aghplctools/indirect.py
aghplctools/local_paths.py
aghplctools/data/__init__.py
aghplctools/data/batch.py
aghplctools/data/sample.py
aghplctools/data/time_course.py
aghplctools/ingestion/__init__.py
aghplctools/ingestion/csv.py
aghplctools/ingestion/text.py
aghplctools-4.8.8.dist-info/LICENSE
aghplctools-4.8.8.dist-info/METADATA
aghplctools-4.8.8.dist-info/WHEEL
aghplctools-4.8.8.dist-info/top_level.txt
aghplctools-4.8.8.dist-info/RECORD
