Metadata-Version: 2.1
Name: aghplctools
Version: 4.8.8
Summary: Interaction package for Agilent ChemStation report files
Home-page: https://gitlab.com/heingroup/aghplctools
Author: Lars Yunker / Hein Group
License: Copyright 2019 Lars Yunker / Hein Group
Project-URL: Documentation, https://aghplctools.readthedocs.io/en/latest/
Project-URL: Hein Group, https://groups.chem.ubc.ca/jheints1/
Classifier: Programming Language :: Python :: 3
Classifier: License :: OSI Approved :: MIT License
Classifier: Development Status :: 4 - Beta
Classifier: Intended Audience :: Science/Research
Classifier: Topic :: Scientific/Engineering :: Chemistry
Classifier: Topic :: Scientific/Engineering :: Information Analysis
Classifier: Operating System :: Microsoft :: Windows
Classifier: Natural Language :: English
Requires-Python: >=3.8
License-File: LICENSE
Requires-Dist: numpy
Requires-Dist: matplotlib >=3.0.3
Requires-Dist: tqdm
Requires-Dist: unithandler >=1.3.3
Requires-Dist: openpyxl >=2.6.2
Requires-Dist: hein-utilities >=3.5
Requires-Dist: aston >=0.7.0
